openlp/.version
openlp/__init__.py
openlp/__main__.py
openlp/core/__init__.py
openlp/core/app.py
openlp/core/loader.py
openlp/core/resources.py
openlp/core/server.py
openlp/core/state.py
openlp/core/threading.py
openlp/core/version.py
openlp/core/api/__init__.py
openlp/core/api/deploy.py
openlp/core/api/lib.py
openlp/core/api/main.py
openlp/core/api/poll.py
openlp/core/api/tab.py
openlp/core/api/websockets.py
openlp/core/api/websocketspoll.py
openlp/core/api/http/__init__.py
openlp/core/api/http/server.py
openlp/core/api/versions/__init__.py
openlp/core/api/versions/v1/__init__.py
openlp/core/api/versions/v1/controller.py
openlp/core/api/versions/v1/core.py
openlp/core/api/versions/v1/plugins.py
openlp/core/api/versions/v1/service.py
openlp/core/api/versions/v2/__init__.py
openlp/core/api/versions/v2/controller.py
openlp/core/api/versions/v2/core.py
openlp/core/api/versions/v2/plugins.py
openlp/core/api/versions/v2/service.py
openlp/core/common/__init__.py
openlp/core/common/actions.py
openlp/core/common/applocation.py
openlp/core/common/enum.py
openlp/core/common/handlers.py
openlp/core/common/httputils.py
openlp/core/common/i18n.py
openlp/core/common/json.py
openlp/core/common/mime.py
openlp/core/common/mixins.py
openlp/core/common/path.py
openlp/core/common/platform.py
openlp/core/common/registry.py
openlp/core/common/settings.py
openlp/core/common/utils.py
openlp/core/db/__init__.py
openlp/core/db/helpers.py
openlp/core/db/manager.py
openlp/core/db/mixins.py
openlp/core/db/types.py
openlp/core/db/upgrades.py
openlp/core/display/__init__.py
openlp/core/display/render.py
openlp/core/display/screens.py
openlp/core/display/webengine.py
openlp/core/display/window.py
openlp/core/display/html/black.css
openlp/core/display/html/checkerboard.png
openlp/core/display/html/display-init.js
openlp/core/display/html/display.css
openlp/core/display/html/display.html
openlp/core/display/html/display.js
openlp/core/display/html/openlp-splash-screen.png
OpenLP-3.9.1.dist-info/LICENSE
OpenLP-3.9.1.dist-info/METADATA
OpenLP-3.9.1.dist-info/WHEEL
OpenLP-3.9.1.dist-info/entry_points.txt
OpenLP-3.9.1.dist-info/top_level.txt
OpenLP-3.9.1.dist-info/RECORD
