Metadata-Version: 2.1
Name: OpenLP
Version: 3.9.1
Summary: Open source Church presentation and lyrics projection application.
Home-page: https://openlp.org/
Author: Raoul Snyman
Author-email: raoulsnyman@openlp.org
License: GPL-3.0-or-later
Keywords: open source church presentation lyrics projection song bible display project
Classifier: Development Status :: 5 - Production/Stable
Classifier: Environment :: MacOS X
Classifier: Environment :: Win32 (MS Windows)
Classifier: Environment :: X11 Applications
Classifier: Environment :: X11 Applications :: Qt
Classifier: Intended Audience :: End Users/Desktop
Classifier: Intended Audience :: Religion
Classifier: License :: OSI Approved :: GNU General Public License v3 or later (GPLv3+)
Classifier: Natural Language :: Afrikaans
Classifier: Natural Language :: Dutch
Classifier: Natural Language :: English
Classifier: Natural Language :: French
Classifier: Natural Language :: German
Classifier: Natural Language :: Hungarian
Classifier: Natural Language :: Indonesian
Classifier: Natural Language :: Japanese
Classifier: Natural Language :: Norwegian
Classifier: Natural Language :: Portuguese (Brazilian)
Classifier: Natural Language :: Russian
Classifier: Natural Language :: Swedish
Classifier: Operating System :: MacOS :: MacOS X
Classifier: Operating System :: Microsoft :: Windows
Classifier: Operating System :: POSIX :: BSD :: FreeBSD
Classifier: Operating System :: POSIX :: Linux
Classifier: Programming Language :: Python
Classifier: Programming Language :: Python :: 3
Classifier: Topic :: Desktop Environment :: Gnome
Classifier: Topic :: Desktop Environment :: K Desktop Environment (KDE)
Classifier: Topic :: Multimedia
Classifier: Topic :: Multimedia :: Graphics :: Presentation
Classifier: Topic :: Multimedia :: Sound/Audio
Classifier: Topic :: Multimedia :: Video
Classifier: Topic :: Religion
Requires-Python: >=3.9
License-File: LICENSE
Requires-Dist: Mako
Requires-Dist: PyICU
Requires-Dist: PySide6>=6.8
Requires-Dist: QtAwesome
Requires-Dist: SQLAlchemy
Requires-Dist: alembic
Requires-Dist: beautifulsoup4
Requires-Dist: chardet
Requires-Dist: flask
Requires-Dist: flask-cors
Requires-Dist: lxml
Requires-Dist: packaging
Requires-Dist: platformdirs
Requires-Dist: qrcode
Requires-Dist: requests
Requires-Dist: waitress
Requires-Dist: websockets
Requires-Dist: Pyro5; platform_system == "Darwin"
Requires-Dist: pyobjc; platform_system == "Darwin"
Requires-Dist: pyobjc-framework-Cocoa; platform_system == "Darwin"
Requires-Dist: dbus-python; platform_system == "Linux"
Requires-Dist: distro; platform_system == "Linux"
Requires-Dist: pywin32; platform_system == "Windows"
Provides-Extra: darkstyle
Requires-Dist: QDarkStyle; extra == "darkstyle"
Provides-Extra: mysql
Requires-Dist: PyMySQL; extra == "mysql"
Provides-Extra: odbc
Requires-Dist: pyodbc; extra == "odbc"
Provides-Extra: postgresql
Requires-Dist: psycopg2-binary; extra == "postgresql"
Provides-Extra: spellcheck
Requires-Dist: pyenchant>=1.6; extra == "spellcheck"
Provides-Extra: sword-bibles
Requires-Dist: pysword; extra == "sword-bibles"
Provides-Extra: test
Requires-Dist: flake8; extra == "test"
Requires-Dist: pyodbc; extra == "test"
Requires-Dist: pysword; extra == "test"
Requires-Dist: pytest; extra == "test"
Requires-Dist: pytest-qt; extra == "test"
